pytket/extensions/ionq/__init__.py
pytket/extensions/ionq/_metadata.py
pytket/extensions/ionq/py.typed
pytket/extensions/ionq/backends/__init__.py
pytket/extensions/ionq/backends/config.py
pytket/extensions/ionq/backends/ionq.py
pytket/extensions/ionq/backends/ionq_convert.py
pytket_ionq-0.23.0.dist-info/LICENSE
pytket_ionq-0.23.0.dist-info/METADATA
pytket_ionq-0.23.0.dist-info/WHEEL
pytket_ionq-0.23.0.dist-info/top_level.txt
pytket_ionq-0.23.0.dist-info/RECORD
