Metadata-Version: 2.1
Name: pytket-ionq
Version: 0.23.0
Summary: Extension for pytket, providing access to IONQ backends
Author: TKET development team
Author-email: tket-support@cambridgequantum.com
License: Apache 2
Project-URL: Documentation, https://cqcl.github.io/pytket-ionq/api/index.html
Project-URL: Source, https://github.com/CQCL/pytket-ionq
Project-URL: Tracker, https://github.com/CQCL/pytket-ionq/issues
Classifier: Environment :: Console
Classifier: Programming Language :: Python :: 3.8
Classifier: Programming Language :: Python :: 3.9
Classifier: Programming Language :: Python :: 3.10
Classifier: License :: OSI Approved :: Apache Software License
Classifier: Operating System :: MacOS :: MacOS X
Classifier: Operating System :: POSIX :: Linux
Classifier: Operating System :: Microsoft :: Windows
Classifier: Intended Audience :: Developers
Classifier: Intended Audience :: Science/Research
Classifier: Topic :: Scientific/Engineering
Requires-Python: >=3.8
License-File: LICENSE
Requires-Dist: pytket (~=1.9)
Requires-Dist: requests (~=2.22)
Requires-Dist: types-requests
